MANIFEST.in
setup.py
gexcel/README.md
gexcel/__init__.py
gexcel/reader.py
gexcel/writer.py
gexcel.egg-info/PKG-INFO
gexcel.egg-info/SOURCES.txt
gexcel.egg-info/dependency_links.txt
gexcel.egg-info/requires.txt
gexcel.egg-info/top_level.txt