Metadata-Version: 2.1
Name: gexcel
Version: 1.0.5
Summary: 一个 excel 便捷读取插入工具
Home-page: https://github.com/Leviathangk/gexcel
Author: 郭一会儿
Author-email: 1015295213@qq.com
License: MIT Licence
Keywords: excel,openpyxl,xlsxwriter
Platform: any
